yunoCTS
