Metadata-Version: 2.1
Name: yunoCTS
Version: 0.2
Summary: SDK Yuno
Home-page: https://pypi.org/project/yunocts
Author: SDK_PS
Author-email: payments@monetizze.com.br
License: MIT License
Keywords: yuno
License-File: LICENSE
